{
 "f": [
  {
   "__tuple__": true, 
   "items": [
    "", 
    0, 
    2147483647, 
    "code_explorer_custom_root_folder_name"
   ]
  }, 
  {
   "__tuple__": true, 
   "items": [
    "/2147483647", 
    0, 
    "3vYFdoiVEe+4iU1Bhw03IW", 
    "\u5c0f\u602a"
   ]
  }, 
  {
   "__tuple__": true, 
   "items": [
    "/2147483647", 
    1, 
    "JJ5xFXpVEe+WOVuZB4f+HW", 
    "\u602a\u7269\u9884\u5236"
   ]
  }, 
  {
   "__tuple__": true, 
   "items": [
    "/2147483647", 
    2, 
    "oPWd0oiWEe+0N01Bhw03IS", 
    "\u9996\u9886"
   ]
  }, 
  {
   "__tuple__": true, 
   "items": [
    "/2147483647", 
    3, 
    "YufsY4icEe+outuzVbVKR5", 
    "h"
   ]
  }
 ], 
 "d": {
  "134252882": {
   "__tuple__": true, 
   "items": [
    "JJ5xFXpVEe+WOVuZB4f+HW", 
    0
   ]
  }, 
  "134246663": {
   "__tuple__": true, 
   "items": [
    "JJ5xFXpVEe+WOVuZB4f+HW", 
    1
   ]
  }, 
  "134245571": {
   "__tuple__": true, 
   "items": [
    "JJ5xFXpVEe+WOVuZB4f+HW", 
    2
   ]
  }, 
  "134224183": {
   "__tuple__": true, 
   "items": [
    "JJ5xFXpVEe+WOVuZB4f+HW", 
    3
   ]
  }, 
  "134279288": {
   "__tuple__": true, 
   "items": [
    "JJ5xFXpVEe+WOVuZB4f+HW", 
    4
   ]
  }, 
  "134270288": {
   "__tuple__": true, 
   "items": [
    "JJ5xFXpVEe+WOVuZB4f+HW", 
    5
   ]
  }, 
  "134277211": {
   "__tuple__": true, 
   "items": [
    "oPWd0oiWEe+0N01Bhw03IS", 
    0
   ]
  }, 
  "10101001": {
   "__tuple__": true, 
   "items": [
    "YufsY4icEe+outuzVbVKR5", 
    0
   ]
  }, 
  "10101002": {
   "__tuple__": true, 
   "items": [
    "YufsY4icEe+outuzVbVKR5", 
    1
   ]
  }, 
  "10101003": {
   "__tuple__": true, 
   "items": [
    "YufsY4icEe+outuzVbVKR5", 
    2
   ]
  }, 
  "10101004": {
   "__tuple__": true, 
   "items": [
    "YufsY4icEe+outuzVbVKR5", 
    3
   ]
  }, 
  "10101005": {
   "__tuple__": true, 
   "items": [
    "YufsY4icEe+outuzVbVKR5", 
    4
   ]
  }, 
  "10101006": {
   "__tuple__": true, 
   "items": [
    "YufsY4icEe+outuzVbVKR5", 
    5
   ]
  }, 
  "10101007": {
   "__tuple__": true, 
   "items": [
    "YufsY4icEe+outuzVbVKR5", 
    6
   ]
  }, 
  "10101008": {
   "__tuple__": true, 
   "items": [
    "YufsY4icEe+outuzVbVKR5", 
    7
   ]
  }, 
  "10101009": {
   "__tuple__": true, 
   "items": [
    "YufsY4icEe+outuzVbVKR5", 
    8
   ]
  }, 
  "10101010": {
   "__tuple__": true, 
   "items": [
    "YufsY4icEe+outuzVbVKR5", 
    9
   ]
  }, 
  "10101011": {
   "__tuple__": true, 
   "items": [
    "YufsY4icEe+outuzVbVKR5", 
    10
   ]
  }, 
  "10101013": {
   "__tuple__": true, 
   "items": [
    "YufsY4icEe+outuzVbVKR5", 
    11
   ]
  }, 
  "10101012": {
   "__tuple__": true, 
   "items": [
    "YufsY4icEe+outuzVbVKR5", 
    12
   ]
  }, 
  "10101014": {
   "__tuple__": true, 
   "items": [
    "YufsY4icEe+outuzVbVKR5", 
    13
   ]
  }, 
  "10101015": {
   "__tuple__": true, 
   "items": [
    "YufsY4icEe+outuzVbVKR5", 
    14
   ]
  }, 
  "10101016": {
   "__tuple__": true, 
   "items": [
    "YufsY4icEe+outuzVbVKR5", 
    15
   ]
  }, 
  "10101017": {
   "__tuple__": true, 
   "items": [
    "YufsY4icEe+outuzVbVKR5", 
    16
   ]
  }, 
  "10101018": {
   "__tuple__": true, 
   "items": [
    "YufsY4icEe+outuzVbVKR5", 
    17
   ]
  }, 
  "10101019": {
   "__tuple__": true, 
   "items": [
    "YufsY4icEe+outuzVbVKR5", 
    18
   ]
  }, 
  "10101020": {
   "__tuple__": true, 
   "items": [
    "YufsY4icEe+outuzVbVKR5", 
    19
   ]
  }, 
  "10101021": {
   "__tuple__": true, 
   "items": [
    "YufsY4icEe+outuzVbVKR5", 
    20
   ]
  }, 
  "10101022": {
   "__tuple__": true, 
   "items": [
    "YufsY4icEe+outuzVbVKR5", 
    21
   ]
  }, 
  "10101023": {
   "__tuple__": true, 
   "items": [
    "YufsY4icEe+outuzVbVKR5", 
    22
   ]
  }, 
  "10101024": {
   "__tuple__": true, 
   "items": [
    "YufsY4icEe+outuzVbVKR5", 
    23
   ]
  }, 
  "10101025": {
   "__tuple__": true, 
   "items": [
    "YufsY4icEe+outuzVbVKR5", 
    24
   ]
  }, 
  "10101026": {
   "__tuple__": true, 
   "items": [
    "YufsY4icEe+outuzVbVKR5", 
    25
   ]
  }, 
  "10101027": {
   "__tuple__": true, 
   "items": [
    "YufsY4icEe+outuzVbVKR5", 
    26
   ]
  }, 
  "10101028": {
   "__tuple__": true, 
   "items": [
    "YufsY4icEe+outuzVbVKR5", 
    27
   ]
  }, 
  "10101029": {
   "__tuple__": true, 
   "items": [
    "YufsY4icEe+outuzVbVKR5", 
    28
   ]
  }, 
  "10101030": {
   "__tuple__": true, 
   "items": [
    "YufsY4icEe+outuzVbVKR5", 
    29
   ]
  }, 
  "10101031": {
   "__tuple__": true, 
   "items": [
    "YufsY4icEe+outuzVbVKR5", 
    30
   ]
  }, 
  "10101032": {
   "__tuple__": true, 
   "items": [
    "YufsY4icEe+outuzVbVKR5", 
    31
   ]
  }, 
  "10101033": {
   "__tuple__": true, 
   "items": [
    "YufsY4icEe+outuzVbVKR5", 
    32
   ]
  }, 
  "10101034": {
   "__tuple__": true, 
   "items": [
    "YufsY4icEe+outuzVbVKR5", 
    33
   ]
  }, 
  "10101035": {
   "__tuple__": true, 
   "items": [
    "YufsY4icEe+outuzVbVKR5", 
    34
   ]
  }, 
  "10101036": {
   "__tuple__": true, 
   "items": [
    "YufsY4icEe+outuzVbVKR5", 
    35
   ]
  }, 
  "10101037": {
   "__tuple__": true, 
   "items": [
    "YufsY4icEe+outuzVbVKR5", 
    36
   ]
  }, 
  "10101038": {
   "__tuple__": true, 
   "items": [
    "YufsY4icEe+outuzVbVKR5", 
    37
   ]
  }, 
  "10101039": {
   "__tuple__": true, 
   "items": [
    "YufsY4icEe+outuzVbVKR5", 
    38
   ]
  }, 
  "10101040": {
   "__tuple__": true, 
   "items": [
    "YufsY4icEe+outuzVbVKR5", 
    39
   ]
  }, 
  "10101041": {
   "__tuple__": true, 
   "items": [
    "YufsY4icEe+outuzVbVKR5", 
    40
   ]
  }, 
  "10101042": {
   "__tuple__": true, 
   "items": [
    "YufsY4icEe+outuzVbVKR5", 
    41
   ]
  }, 
  "10101043": {
   "__tuple__": true, 
   "items": [
    "YufsY4icEe+outuzVbVKR5", 
    42
   ]
  }, 
  "10101044": {
   "__tuple__": true, 
   "items": [
    "YufsY4icEe+outuzVbVKR5", 
    43
   ]
  }, 
  "10101045": {
   "__tuple__": true, 
   "items": [
    "YufsY4icEe+outuzVbVKR5", 
    44
   ]
  }, 
  "10101046": {
   "__tuple__": true, 
   "items": [
    "YufsY4icEe+outuzVbVKR5", 
    45
   ]
  }, 
  "10101047": {
   "__tuple__": true, 
   "items": [
    "YufsY4icEe+outuzVbVKR5", 
    46
   ]
  }, 
  "10101048": {
   "__tuple__": true, 
   "items": [
    "YufsY4icEe+outuzVbVKR5", 
    47
   ]
  }, 
  "10101049": {
   "__tuple__": true, 
   "items": [
    "YufsY4icEe+outuzVbVKR5", 
    48
   ]
  }, 
  "10101050": {
   "__tuple__": true, 
   "items": [
    "YufsY4icEe+outuzVbVKR5", 
    49
   ]
  }, 
  "10101051": {
   "__tuple__": true, 
   "items": [
    "YufsY4icEe+outuzVbVKR5", 
    50
   ]
  }, 
  "10101052": {
   "__tuple__": true, 
   "items": [
    "YufsY4icEe+outuzVbVKR5", 
    51
   ]
  }, 
  "10101053": {
   "__tuple__": true, 
   "items": [
    "YufsY4icEe+outuzVbVKR5", 
    52
   ]
  }, 
  "10101054": {
   "__tuple__": true, 
   "items": [
    "YufsY4icEe+outuzVbVKR5", 
    53
   ]
  }, 
  "10101055": {
   "__tuple__": true, 
   "items": [
    "YufsY4icEe+outuzVbVKR5", 
    54
   ]
  }, 
  "10101056": {
   "__tuple__": true, 
   "items": [
    "YufsY4icEe+outuzVbVKR5", 
    55
   ]
  }, 
  "10101057": {
   "__tuple__": true, 
   "items": [
    "YufsY4icEe+outuzVbVKR5", 
    56
   ]
  }, 
  "10101058": {
   "__tuple__": true, 
   "items": [
    "YufsY4icEe+outuzVbVKR5", 
    57
   ]
  }, 
  "10101059": {
   "__tuple__": true, 
   "items": [
    "YufsY4icEe+outuzVbVKR5", 
    58
   ]
  }, 
  "10101060": {
   "__tuple__": true, 
   "items": [
    "YufsY4icEe+outuzVbVKR5", 
    59
   ]
  }, 
  "10101061": {
   "__tuple__": true, 
   "items": [
    "YufsY4icEe+outuzVbVKR5", 
    60
   ]
  }, 
  "10101062": {
   "__tuple__": true, 
   "items": [
    "YufsY4icEe+outuzVbVKR5", 
    61
   ]
  }, 
  "10101063": {
   "__tuple__": true, 
   "items": [
    "YufsY4icEe+outuzVbVKR5", 
    62
   ]
  }, 
  "10101064": {
   "__tuple__": true, 
   "items": [
    "YufsY4icEe+outuzVbVKR5", 
    63
   ]
  }, 
  "10101065": {
   "__tuple__": true, 
   "items": [
    "YufsY4icEe+outuzVbVKR5", 
    64
   ]
  }, 
  "10101066": {
   "__tuple__": true, 
   "items": [
    "YufsY4icEe+outuzVbVKR5", 
    65
   ]
  }, 
  "10101067": {
   "__tuple__": true, 
   "items": [
    "YufsY4icEe+outuzVbVKR5", 
    66
   ]
  }, 
  "10101068": {
   "__tuple__": true, 
   "items": [
    "YufsY4icEe+outuzVbVKR5", 
    67
   ]
  }, 
  "10101069": {
   "__tuple__": true, 
   "items": [
    "YufsY4icEe+outuzVbVKR5", 
    68
   ]
  }, 
  "10101070": {
   "__tuple__": true, 
   "items": [
    "YufsY4icEe+outuzVbVKR5", 
    69
   ]
  }, 
  "10101071": {
   "__tuple__": true, 
   "items": [
    "YufsY4icEe+outuzVbVKR5", 
    70
   ]
  }, 
  "10101072": {
   "__tuple__": true, 
   "items": [
    "YufsY4icEe+outuzVbVKR5", 
    71
   ]
  }, 
  "10101073": {
   "__tuple__": true, 
   "items": [
    "YufsY4icEe+outuzVbVKR5", 
    72
   ]
  }, 
  "10101074": {
   "__tuple__": true, 
   "items": [
    "YufsY4icEe+outuzVbVKR5", 
    73
   ]
  }, 
  "10101075": {
   "__tuple__": true, 
   "items": [
    "YufsY4icEe+outuzVbVKR5", 
    74
   ]
  }, 
  "10101076": {
   "__tuple__": true, 
   "items": [
    "YufsY4icEe+outuzVbVKR5", 
    75
   ]
  }, 
  "10101077": {
   "__tuple__": true, 
   "items": [
    "YufsY4icEe+outuzVbVKR5", 
    76
   ]
  }, 
  "10101078": {
   "__tuple__": true, 
   "items": [
    "YufsY4icEe+outuzVbVKR5", 
    77
   ]
  }, 
  "10101079": {
   "__tuple__": true, 
   "items": [
    "YufsY4icEe+outuzVbVKR5", 
    78
   ]
  }, 
  "10101080": {
   "__tuple__": true, 
   "items": [
    "YufsY4icEe+outuzVbVKR5", 
    79
   ]
  }, 
  "10101081": {
   "__tuple__": true, 
   "items": [
    "YufsY4icEe+outuzVbVKR5", 
    80
   ]
  }, 
  "10101082": {
   "__tuple__": true, 
   "items": [
    "YufsY4icEe+outuzVbVKR5", 
    81
   ]
  }, 
  "10101083": {
   "__tuple__": true, 
   "items": [
    "YufsY4icEe+outuzVbVKR5", 
    82
   ]
  }, 
  "10101084": {
   "__tuple__": true, 
   "items": [
    "YufsY4icEe+outuzVbVKR5", 
    83
   ]
  }, 
  "10101085": {
   "__tuple__": true, 
   "items": [
    "YufsY4icEe+outuzVbVKR5", 
    84
   ]
  }, 
  "10101086": {
   "__tuple__": true, 
   "items": [
    "YufsY4icEe+outuzVbVKR5", 
    85
   ]
  }, 
  "10101087": {
   "__tuple__": true, 
   "items": [
    "YufsY4icEe+outuzVbVKR5", 
    86
   ]
  }, 
  "10101088": {
   "__tuple__": true, 
   "items": [
    "YufsY4icEe+outuzVbVKR5", 
    87
   ]
  }, 
  "10101089": {
   "__tuple__": true, 
   "items": [
    "YufsY4icEe+outuzVbVKR5", 
    88
   ]
  }, 
  "10101090": {
   "__tuple__": true, 
   "items": [
    "YufsY4icEe+outuzVbVKR5", 
    89
   ]
  }, 
  "10101091": {
   "__tuple__": true, 
   "items": [
    "YufsY4icEe+outuzVbVKR5", 
    90
   ]
  }, 
  "10101092": {
   "__tuple__": true, 
   "items": [
    "YufsY4icEe+outuzVbVKR5", 
    91
   ]
  }, 
  "10101093": {
   "__tuple__": true, 
   "items": [
    "YufsY4icEe+outuzVbVKR5", 
    92
   ]
  }, 
  "10101094": {
   "__tuple__": true, 
   "items": [
    "YufsY4icEe+outuzVbVKR5", 
    93
   ]
  }, 
  "10101095": {
   "__tuple__": true, 
   "items": [
    "YufsY4icEe+outuzVbVKR5", 
    94
   ]
  }, 
  "10101096": {
   "__tuple__": true, 
   "items": [
    "YufsY4icEe+outuzVbVKR5", 
    95
   ]
  }, 
  "10101097": {
   "__tuple__": true, 
   "items": [
    "YufsY4icEe+outuzVbVKR5", 
    96
   ]
  }, 
  "10101098": {
   "__tuple__": true, 
   "items": [
    "YufsY4icEe+outuzVbVKR5", 
    97
   ]
  }, 
  "10101099": {
   "__tuple__": true, 
   "items": [
    "YufsY4icEe+outuzVbVKR5", 
    98
   ]
  }, 
  "10101100": {
   "__tuple__": true, 
   "items": [
    "YufsY4icEe+outuzVbVKR5", 
    99
   ]
  }
 }
}